pm4pyserialization/__init__.py
pm4pyserialization/objects/__init__.py
pm4pyserialization/objects/log/__init__.py
pm4pyserialization/objects/log/deserialization/__init__.py
pm4pyserialization/objects/log/deserialization/deserializer.py
pm4pyserialization/objects/log/deserialization/variants/__init__.py
pm4pyserialization/objects/log/deserialization/variants/parquet_dataframe.py
pm4pyserialization/objects/log/deserialization/variants/pyarrow_event_log.py
pm4pyserialization/objects/log/deserialization/variants/pyarrow_event_stream.py
pm4pyserialization/objects/log/exporter/__init__.py
pm4pyserialization/objects/log/exporter/parquet/__init__.py
pm4pyserialization/objects/log/exporter/parquet/exporter.py
pm4pyserialization/objects/log/exporter/parquet/variants/__init__.py
pm4pyserialization/objects/log/exporter/parquet/variants/pandas.py
pm4pyserialization/objects/log/exporter/parquet/variants/pyarrow.py
pm4pyserialization/objects/log/importer/__init__.py
pm4pyserialization/objects/log/importer/parquet/__init__.py
pm4pyserialization/objects/log/importer/parquet/importer.py
pm4pyserialization/objects/log/importer/parquet/parameters.py
pm4pyserialization/objects/log/importer/parquet/variants/__init__.py
pm4pyserialization/objects/log/importer/parquet/variants/fastparquet.py
pm4pyserialization/objects/log/importer/parquet/variants/pyarrow.py
pm4pyserialization/objects/log/serialization/__init__.py
pm4pyserialization/objects/log/serialization/serializer.py
pm4pyserialization/objects/log/serialization/variants/__init__.py
pm4pyserialization/objects/log/serialization/variants/parquet_dataframe.py
pm4pyserialization/objects/log/serialization/variants/pyarrow_event_log.py
pm4pyserialization/objects/log/serialization/variants/pyarrow_event_stream.py
pm4pyserialization-0.0.1.dist-info/LICENSE
pm4pyserialization-0.0.1.dist-info/METADATA
pm4pyserialization-0.0.1.dist-info/WHEEL
pm4pyserialization-0.0.1.dist-info/top_level.txt
pm4pyserialization-0.0.1.dist-info/RECORD
