Metadata-Version: 2.1
Name: pm4pyserialization
Version: 0.0.1
Summary: Process Mining for Python (PM4Py) - Support for advanced serializations
Home-page: http://www.pm4py.org
Author: Fraunhofer Institute for Applied Technology
Author-email: pm4py@fit.fraunhofer.de
License: GPL 3.0
Project-URL: Documentation, http://www.pm4py.org
Project-URL: Source, https://github.com/pm4py/pm4py-source
Project-URL: Tracker, https://github.com/pm4py/pm4py-source/issues
Platform: UNKNOWN
Requires-Dist: pm4py (>=2.0.0)
Requires-Dist: pyarrow (>=1.0.1)
